sloopengine/__init__.py
sloopengine/config.py
sloopengine/agent/__init__.py
sloopengine/includes/__init__.py
sloopengine/includes/common.py
sloopengine/resource/__init__.py
sloopengine/resource/credential.py
sloopengine_cli-2.1.1.dist-info/LICENSE
sloopengine_cli-2.1.1.dist-info/METADATA
sloopengine_cli-2.1.1.dist-info/WHEEL
sloopengine_cli-2.1.1.dist-info/entry_points.txt
sloopengine_cli-2.1.1.dist-info/top_level.txt
sloopengine_cli-2.1.1.dist-info/zip-safe
sloopengine_cli-2.1.1.dist-info/RECORD
