Metadata-Version: 2.1
Name: sloopengine-cli
Version: 2.1.1
Summary: SloopEngine CLI for managing resources and agent.
Home-page: https://github.com/sloopstash/sloopengine-cli
Author: SloopEngine DevOps
Author-email: devops@sloopengine.io
License: Apache License 2.0
Project-URL: Source, https://github.com/sloopstash/sloopengine-cli
Project-URL: Issues, https://github.com/sloopstash/sloopengine-cli/issues
Platform: UNKNOWN
Classifier: Programming Language :: Python :: 3.6
Classifier: Programming Language :: Python :: 3.7
Classifier: Programming Language :: Python :: 3.8
Classifier: Programming Language :: Python :: 3.9
Classifier: License :: OSI Approved :: Apache Software License
Classifier: Operating System :: OS Independent
Requires-Python: >=3.6
License-File: LICENSE
Requires-Dist: subprocess32 (==3.5.4)
Requires-Dist: requests (==2.26.0)
Requires-Dist: validators (==0.18.2)
Requires-Dist: termcolor (==1.1.0)
